RTS_Twitch/Authenticate.py
RTS_Twitch/EventSub.py
RTS_Twitch/EventSubscriptions.py
RTS_Twitch/Scopes.py
RTS_Twitch/__init__.py
RTS_Twitch/authpaths.py
RTS_Twitch/memory.py
RTS_Twitch/overwrites.py
RTS_Twitch/toolset.py
RTS_Twitch/api/__init__.py
RTS_Twitch/api/ads.py
RTS_Twitch/api/analytics.py
RTS_Twitch/api/bits.py
RTS_Twitch/api/channel_points.py
RTS_Twitch/api/channels.py
RTS_Twitch/api/charity.py
RTS_Twitch/api/chat.py
RTS_Twitch/api/clips.py
RTS_Twitch/api/content_class_lable.py
RTS_Twitch/api/entitlements.py
RTS_Twitch/api/games.py
RTS_Twitch/api/goals.py
RTS_Twitch/api/moderation.py
RTS_Twitch/api/streams.py
RTS_Twitch/api/subscriptions.py
RTS_Twitch/api/users.py
rts_twitchbot-1.7.dist-info/LICENCE
rts_twitchbot-1.7.dist-info/METADATA
rts_twitchbot-1.7.dist-info/WHEEL
rts_twitchbot-1.7.dist-info/top_level.txt
rts_twitchbot-1.7.dist-info/RECORD
