Metadata-Version: 2.1
Name: rts-twitchbot
Version: 1.7
Summary: A RTS Package to create your own Twitch Bot.
Home-page: UNKNOWN
Author: RandomTimeTV
Author-email: dergepanzerte1@gmail.com
License: Unlicensed
Platform: UNKNOWN
Classifier: Development Status :: 3 - Alpha
Classifier: License :: OSI Approved :: MIT License
Classifier: Programming Language :: Python :: 3.6
Classifier: Programming Language :: Python :: 3.7
Classifier: Programming Language :: Python :: 3.8
Classifier: Programming Language :: Python :: 3.9
Classifier: Programming Language :: Python :: 3.10
Classifier: Programming Language :: Python :: 3.11
Classifier: Programming Language :: Python :: 3.12
License-File: LICENCE
Requires-Dist: rts-webuibuilder
Requires-Dist: rts-docsbuilder
Requires-Dist: extrautilities
Requires-Dist: websockets
